unifs/config.py
unifs/exceptions.py
unifs/file_system.py
unifs/logging.py
unifs/tui.py
unifs/util.py
unifs/cli/conf.py
unifs/cli/fs.py
unifs/cli/impl.py
unifs/cli/main.py
unifs-1.1.0.dist-info/LICENSE
unifs-1.1.0.dist-info/METADATA
unifs-1.1.0.dist-info/WHEEL
unifs-1.1.0.dist-info/entry_points.txt
unifs-1.1.0.dist-info/top_level.txt
unifs-1.1.0.dist-info/RECORD
