Metadata-Version: 2.1
Name: unifs
Version: 1.1.0
Summary: Unified FS-like CLI for S3, GCS, ADLS, HDFS, SMB, Dropbox, Google Drive, and dozens of other file systems
Author: candidtim
License: BSD 3-Clause License
Project-URL: Homepage, https://github.com/candidtim/unifs
Project-URL: Repository, https://github.com/candidtim/unifs
Project-URL: Documentation, https://github.com/candidtim/unifs/blob/main/README.md
Project-URL: Issues, https://github.com/candidtim/unifs/issues
Keywords: fs,shell
Classifier: License :: OSI Approved :: BSD License
Classifier: Development Status :: 5 - Production/Stable
Classifier: Intended Audience :: Developers
Classifier: Intended Audience :: End Users/Desktop
Classifier: Programming Language :: Python :: 3
Classifier: Operating System :: OS Independent
Classifier: Environment :: Console
Classifier: Topic :: Desktop Environment :: File Managers
Classifier: Topic :: System :: Filesystems
Classifier: Topic :: Utilities
Requires-Python: >=3.7
License-File: LICENSE
Requires-Dist: click (<9,>=8.1.3)
Requires-Dist: fsspec (>=2022.11)
Requires-Dist: tomli-w (<2,>=1)
Requires-Dist: appdirs (<2,>=1.4.4)
Requires-Dist: dacite (<2,>=1.7.0)
Requires-Dist: tomli (<3,>=2.0.1) ; python_version < "3.11"
Provides-Extra: dev
Requires-Dist: pytest (<8,>=7) ; extra == 'dev'
Requires-Dist: pytest-cov (<5,>=4) ; extra == 'dev'
Requires-Dist: coverage (<8,>=7) ; extra == 'dev'
Requires-Dist: flake8 (<5,>=4) ; extra == 'dev'
Requires-Dist: black (<23,>=22.6.0) ; extra == 'dev'
Requires-Dist: isort (<6,>=5.10.1) ; extra == 'dev'
Requires-Dist: pyright (<2,>=1.1.286) ; extra == 'dev'
